bboxes/__init__.py
bboxes/bboxes.py
bboxes-0.0.1.dist-info/LICENSE
bboxes-0.0.1.dist-info/METADATA
bboxes-0.0.1.dist-info/WHEEL
bboxes-0.0.1.dist-info/top_level.txt
bboxes-0.0.1.dist-info/RECORD
